modetool/__init__.py
modetool/archive.py
modetool/cli.py
modetool/modetool.py
modetool-0.1.0.dist-info/entry_points.txt
modetool-0.1.0.dist-info/WHEEL
modetool-0.1.0.dist-info/METADATA
modetool-0.1.0.dist-info/RECORD
