Metadata-Version: 2.1
Name: modetool
Version: 0.1.0
Summary: 
Author: Chris Coughlan
Author-email: chris@coughlan.io
Requires-Python: >=3.8,<4.0
Classifier: Programming Language :: Python :: 3
Classifier: Programming Language :: Python :: 3.8
Requires-Dist: loguru (>=0.5.1,<0.6.0)
Requires-Dist: py7zr (>=0.7.3,<0.8.0)
